[{
  "track": 1,
  "name": "All This Is - Joe L.'s Studio",
  "length": "02:46",
  "file": "/media/bts"
}, {
  "track": 2,
  "name": "The Forsaken - Broadwing Studio (Final Mix)",
  "length": "08:31",
  "file": "/media/bts"
}, {
  "track": 3,
  "name": "All The King's Men - Broadwing Studio (Final Mix)",
  "length": "05:02",
  "file": "/media/bts"
}, {
  "track": 4,
  "name": "The Forsaken - Broadwing Studio (First Mix)",
  "length": "08:32",
  "file": "/media/bts"
}, {
  "track": 5,
  "name": "All The King's Men - Broadwing Studio (First Mix)",
  "length": "05:05",
  "file": "/media/bts"
}, {
  "track": 6,
  "name": "All This Is - Alternate Cuts",
  "length": "02:49",
  "file": "/media/bts"
}, {
  "track": 7,
  "name": "All The King's Men (Take 1) - Alternate Cuts",
  "length": "05:45",
  "file": "/media/bts"
}, {
  "track": 8,
  "name": "All The King's Men (Take 2) - Alternate Cuts",
  "length": "05:27",
  "file": "/media/bts"
}, {
  "track": 9,
  "name": "Magus - Alternate Cuts",
  "length": "05:46",
  "file": "/media/bts"
}, {
  "track": 10,
  "name": "The State Of Wearing Address (fucked up) - Alternate Cuts",
  "length": "05:25",
  "file": "/media/bts"
}, {
  "track": 11,
  "name": "Magus - Popeye's (New Years '04 - '05)",
  "length": "05:54",
  "file": "/media/bts"
}, {
  "track": 12,
  "name": "On The Waterfront - Popeye's (New Years '04 - '05)",
  "length": "04:41",
  "file": "/media/bts"
}, {
  "track": 13,
  "name": "Trance - Popeye's (New Years '04 - '05)",
  "length": "13:17",
  "file": "/media/bts"
}, {
  "track": 14,
  "name": "The Forsaken - Popeye's (New Years '04 - '05)",
  "length": "08:13",
  "file": "PNY04-05_TF"
}, {
  "track": 15,
  "name": "The State Of Wearing Address - Popeye's (New Years '04 - '05)",
  "length": "07:03",
  "file": "/media/bts"
}, {
  "track": 16,
  "name": "Magus - Popeye's (Valentine's Day '05)",
  "length": "05:44",
  "file": "/media/bts"
}, {
  "track": 17,
  "name": "Trance - Popeye's (Valentine's Day '05)",
  "length": "10:47",
  "file": "/media/bts"
}, {
  "track": 18,
  "name": "The State Of Wearing Address - Popeye's (Valentine's Day '05)",
  "length": "05:37",
  "file": "/media/bts"
}, {
  "track": 19,
  "name": "All This Is - Smith St. Basement (01/08/04)",
  "length": "02:49",
  "file": "/media/bts"
}, {
  "track": 20,
  "name": "Magus - Smith St. Basement (01/08/04)",
  "length": "05:46",
  "file": "/media/bts"
}, {
  "track": 21,
  "name": "Beneath The Painted Eye - Smith St. Basement (06/06/03)",
  "length": "13:08",
  "file": "/media/bts"
}, {
  "track": 22,
  "name": "Innocence - Smith St. Basement (06/06/03)",
  "length": "05:16",
  "file": "/media/bts"
}, {
  "track": 23,
  "name": "Magus - Smith St. Basement (06/06/03)",
  "length": "05:47",
  "file": "/media/bts"
}, {
  "track": 24,
  "name": "Madness Explored - Smith St. Basement (06/06/03)",
  "length": "04:52",
  "file": "/media/bts"
}, {
  "track": 25,
  "name": "The Forsaken - Smith St. Basement (06/06/03)",
  "length": "08:44",
  "file": "/media/bts"
}, {
  "track": 26,
  "name": "All This Is - Smith St. Basement (12/28/03)",
  "length": "03:01",
  "file": "/media/bts"
}, {
  "track": 27,
  "name": "Magus - Smith St. Basement (12/28/03)",
  "length": "06:10",
  "file": "/media/bts"
}, {
  "track": 28,
  "name": "Madness Explored - Smith St. Basement (12/28/03)",
  "length": "05:06",
  "file": "/media/bts"
}, {
  "track": 29,
  "name": "Trance - Smith St. Basement (12/28/03)",
  "length": "12:33",
  "file": "/media/bts"
}, {
  "track": 30,
  "name": "The Forsaken - Smith St. Basement (12/28/03)",
  "length": "08:57",
  "file": "/media/bts"
}, {
  "track": 31,
  "name": "All This Is (Take 1) - Smith St. Basement (Nov. '03)",
  "length": "04:55",
  "file": "/media/bts"
}, {
  "track": 32,
  "name": "All This Is (Take 2) - Smith St. Basement (Nov. '03)",
  "length": "05:46",
  "file": "/media/bts"
}, {
  "track": 33,
  "name": "Beneath The Painted Eye (Take 1) - Smith St. Basement (Nov. '03)",
  "length": "14:06",
  "file": "/media/bts"
}, {
  "track": 34,
  "name": "Beneath The Painted Eye (Take 2) - Smith St. Basement (Nov. '03)",
  "length": "13:26",
  "file": "/media/bts"
}, {
  "track": 35,
  "name": "The Forsaken (Take 1) - Smith St. Basement (Nov. '03)",
  "length": "08:38",
  "file": "/media/bts"
}, {
  "track": 36,
  "name": "The Forsaken (Take 2) - Smith St. Basement (Nov. '03)",
  "length": "08:37",
  "file": "/media/bts"
}]